liangfei_FM/__init__.py
liangfei_FM-0.1.dist-info/METADATA
liangfei_FM-0.1.dist-info/WHEEL
liangfei_FM-0.1.dist-info/top_level.txt
liangfei_FM-0.1.dist-info/RECORD
